wassfast/__init__.py
wassfast/__main__.py
wassfast/_wassfast.py
wassfast/initializer.m
wassfast/netcdfoutput.py
wassfast/plane_avg_recomputed.txt
wassfast/wassfast.py
wassfast/CUDAmatcher/CMakeLists.txt
wassfast/CUDAmatcher/src/cudamatcher.cpp
wassfast/CUDAmatcher/src/cudamatcher.h
wassfast/CUDAmatcher/src/cudamatcherexe.cpp
wassfast/CUDAmatcher/src/hires_timer.hpp
wassfast/PointsReducer/CMakeLists.txt
wassfast/PointsReducer/PointsReducer.py
wassfast/PointsReducer/PointsReducerTest.ipynb
wassfast/PointsReducer/src/pointsreducer.cpp
wassfast/PointsReducer/src/pointsreducer.h
wassfast/WaveFieldVisualize/waveview.py
wassfast/WaveFieldVisualize/waveview2.py
wassfast/analysis/analysis.py
wassfast/analysis/analysis_template.html
wassfast/analysis/analyze_netcdf.ipynb
wassfast/analysis/analyze_synthetic_results.ipynb
wassfast/analysis/curl-ca-bundle.crt
wassfast/analysis/curl.exe
wassfast/cnn/SparseSeriesDataGenerator.py
wassfast/cnn/losses.py
wassfast/cnn/sparsecnn_prediction_test.ipynb
wassfast/cnn/sparsecnn_with_prediction_model.py
wassfast/cnn/sparsenet_models.py
wassfast/cnn/wavenet_models.py
wassfast/cnn/modeldata/2021-06-24_09-08-53_2.h5
wassfast/cnn/modeldata/2021-06-30_16-48-27.h5
wassfast/cnn/modeldata/2021-07-01_12-00-44_3.h5
wassfast/cnn/modeldata/prediction_v1_2020-09-22_16-07-17.h5
wassfast/cvproc/Bicubicdemosaicer.py
wassfast/cvproc/HDF5Appender.py
wassfast/cvproc/camseahomography.py
wassfast/cvproc/dirreader.py
wassfast/cvproc/rawreader.py
wassfast/cvproc/sparsematcher.py
wassfast/cvproc/spectrum.py
wassfast/cvproc/utils.py
wassfast/specfit/__init__.py
wassfast/specfit/gausswin.py
wassfast/specfit/specfit_fft.py
wassfast/specfit/specfit_nfft.py
wassfast/specfit/tukeywin.py
wassfast-1.6.3.dist-info/licenses/LICENSE
wassfast-1.6.3.dist-info/METADATA
wassfast-1.6.3.dist-info/WHEEL
wassfast-1.6.3.dist-info/entry_points.txt
wassfast-1.6.3.dist-info/top_level.txt
wassfast-1.6.3.dist-info/RECORD
