Metadata-Version: 2.4
Name: wassfast
Version: 1.6.3
Summary: The next-generation stereo processing pipeline for sea waves 3D reconstruction.
Author: Filippo Bergamasco
Author-email: filippo.bergamasco@unive.it
License: GPL3
Project-URL: homepage, https://sites.google.com/unive.it/wass
Project-URL: repository, https://gitlab.com/fibe/wassfast
Keywords: WASS,3D,Sea-waves
Classifier: Programming Language :: Python :: 3
Classifier: Development Status :: 4 - Beta
Requires-Python: >=3.12
License-File: LICENSE
Requires-Dist: tensorflow[and-cuda]==2.20
Requires-Dist: protobuf
Requires-Dist: numpy
Requires-Dist: matplotlib
Requires-Dist: netcdf4
Requires-Dist: pyopengl
Requires-Dist: scipy
Requires-Dist: opencv-python
Requires-Dist: tqdm
Requires-Dist: glfw
Requires-Dist: mako
Dynamic: license-file
